{"hash":"d2f3c424ba6bfcdc240717c4a2b8a6b9e4f18d0c","data":{"recommends":{"edges":[{"node":{"publishDate":"2024-05-14T02:32:30.000Z","title":"Alums of MA & PhD","url":"/en/training/b17ef6d19c7a5b1e"}},{"node":{"publishDate":"2024-05-14T02:30:56.000Z","title":"The First Academic Committee","url":"/en/about/e629fa6598d73276"}},{"node":{"publishDate":"2024-05-14T02:29:55.000Z","title":"About Us","url":"/en/about/8527a891e2241369"}},{"node":{"publishDate":"2024-05-14T02:12:42.000Z","title":"Contact Us","url":"/en/about/3fdba35f04dc8c46"}},{"node":{"publishDate":"2024-05-13T09:47:02.000Z","title":"Publications List (2014)","url":"/en/tools/6b51d431df5d7f14"}}]}},"context":{"id":"e629fa6598d73276","title":"The First Academic Committee","publishDate":"2024-05-14T02:30:56.000Z","author":"","photographer":"","content":"<p><strong>Membership of the Academic Committee</strong></p>\r\n\r\n<p>&nbsp;</p>\r\n\r\n<p>Professor&nbsp;<strong>Ming FANG</strong>, China National Radio (CNR).<br />\r\nProfessor&nbsp;<strong>Zhiwei FENG</strong>, a research fellow at the Institute of Applied Linguistics, Ministry of Education (IAL-MOE), and a member of the Academic Committee of IAL-MOE.<br />\r\nProfessor&nbsp;<strong>Changning HUANG</strong>, Microsoft Research Asia.<br />\r\n<strong>Delong JIN</strong>, the State Administration of Radio Film and Television.<br />\r\nProfessor&nbsp;<strong>Xiaohua LI</strong>, Dean of the Graduate School at Communication University of China.<br />\r\nProfessor&nbsp;<strong>Jingchao LU</strong>, Dean of Presentation Art School at Communication University of China.<br />\r\nProfessor&nbsp;<strong>Jianming LU</strong>, Dept. of Chinese Language and Literature at Peking University.<br />\r\n<strong>Jing LUO</strong>, China Central Television (CCTV).<br />\r\nProfessor&nbsp;<strong>Yukun MA</strong>, Presentation Art School at Communication University of China.<br />\r\nProfessor&nbsp;<strong>Jiaxuan SHEN</strong>, Institute of Linguistics, Chinese Academy of Social Sciences.<br />\r\n<strong>Liang WANG</strong>, Beijing Radio Corporation (RBC).<br />\r\nProfessor&nbsp;<strong>Xishuang YAO</strong>, Institute of Applied Linguistics, Ministry of Education (IAL-MOE).<br />\r\nProfessor&nbsp;<strong>Shiwen YU</strong>, Institute of Computational Linguistics at Peking University.<br />\r\nProfessor&nbsp;<strong>Pu ZHANG</strong>, Institute of Applied Linguistics at Beijing Language and Culture University.<br />\r\nProfessor&nbsp;<strong>Song ZHANG</strong>, Presentation Art School at Communication University of China.</p>\r\n\r\n<p>&nbsp;</p>\r\n\r\n<p><br />\r\n<strong>Co-director of Academic Committee</strong></p>\r\n\r\n<p>&nbsp;</p>\r\n\r\n<p>Professor&nbsp;<strong>Yuming LI</strong>, Director of Administration Dept. of Chinese Language and Information in Ministry of Education.<br />\r\nProfessor&nbsp;<strong>Zhiwu SU</strong>, President of Communication University of China.</p>\r\n","category":"关于我们","subCategory":"学术委员","languagee":"en","isActive":1,"isTop":0,"keyWords":"","imgUrl":"http://localhost:3000/images/yshengfiles/20210508.jpg","directionUrl":"","listUrl":"/en/about","subListUrl":""}}